trafficlight.v
 module traffic_control(n_lights,s_lights,e_lights,w_lights,clk,rst_a);

   output reg [2:0] n_lights,s_lights,e_lights,w_lights;
   input      clk;
   input      rst_a;

   reg [2:0] state;

   wire [2:0] north=3'b000;
   wire [2:0] north_y=3'b001;
   wire [2:0] south=3'b010;
   wire [2:0] south_y=3'b011;
   wire [2:0] east=3'b100;
   wire [2:0] east_y=3'b101;
   wire [2:0] west=3'b110;
   wire [2:0] west_y=3'b111;

   reg [2:0] count;


   always @(posedge clk, posedge rst_a)
     begin
        if (rst_a)
            begin
                state=north;
                count =3'b000;
            end
        else
            begin
                case (state)
                north :
                    begin
                        if (count==3'b111)
                            begin
                            count=3'b000;
                            state=north_y;
                            end
                        else
                            begin
                            count=count+3'b001;
                            state=north;
                            end
                    end

                north_y :
                    begin
                        if (count==3'b011)
                            begin
                            count=3'b000;
                            state=south;
                            end
                        else
                            begin
                            count=count+3'b001;
                            state=north_y;
                        end
                    end

               south :
                    begin
                        if (count==3'b111)
                            begin
                            count=3'b0;
                            state=south_y;
                            end
                        else
                            begin
                            count=count+3'b001;
                            state=south;
                        end
                    end

            south_y :
                begin
                    if (count==3'b011)
                        begin
                        count=3'b0;
                        state=east;
                        end
                    else
                        begin
                        count=count+3'b001;
                        state=south_y;
                        end
                    end

            east :
                begin
                    if (count==3'b111)
                        begin
                        count=3'b0;
                        state=east_y;
                        end
                    else
                        begin
                        count=count+3'b001;
                        state=east;
                        end
                    end

            east_y :
                begin
                    if (count==3'b011)
                        begin
                        count=3'b0;
                        state=west;
                        end
                    else
                        begin
                        count=count+3'b001;
                        state=east_y;
                        end
                    end

            west :
                begin
                    if (count==3'b111)
                        begin
                        state=west_y;
                        count=3'b0;
                        end
                    else
                        begin
                        count=count+3'b001;
                        state=west;
                        end
                    end

            west_y :
                begin
                    if (count==3'b011)
                        begin
                        state=north;
                        count=3'b000;
                        end
                    else
                        begin
                        count=count+3'b001;
                        state=west_y;
                        end
                    end
            endcase // case (state)
        end // always @ (state)
    end


always @(state)
     begin
         case (state)
            north :
                begin
                    n_lights = 3'b001;
                    s_lights = 3'b100;
                    e_lights = 3'b100;
                    w_lights = 3'b100;
                end // case: north

            north_y :
                begin
                    n_lights = 3'b010;
                    s_lights = 3'b100;
                    e_lights = 3'b100;
                    w_lights = 3'b100;
                end // case: north_y

            south :
                begin
                    n_lights = 3'b100;
                    s_lights = 3'b001;
                    e_lights = 3'b100;
                    w_lights = 3'b100;
                end // case: south

            south_y :
                begin
                    n_lights = 3'b100;
                    s_lights = 3'b010;
                    e_lights = 3'b100;
                    w_lights = 3'b100;
                end // case: south_y

            west :
                begin
                    n_lights = 3'b100;
                    s_lights = 3'b100;
                    e_lights = 3'b100;
                    w_lights = 3'b001;
                end // case: west

            west_y :
                begin
                    n_lights = 3'b100;
                    s_lights = 3'b100;
                    e_lights = 3'b100;
                    w_lights = 3'b010;
                end // case: west_y

            east :
                begin
                    n_lights = 3'b100;
                    s_lights = 3'b100;
                    e_lights = 3'b001;
                    w_lights = 3'b100;
                end // case: east

            east_y :
                begin
                    n_lights = 3'b100;
                    s_lights = 3'b100;
                    e_lights = 3'b010;
                    w_lights = 3'b100;
                end // case: east_y
            endcase // case (state)
     end // always @ (state)
endmodule




`timescale 1ns/1ps
module traffic_control_tb;

wire [2:0] n_lights,s_lights,e_lights,w_lights;
reg clk,rst_a;
integer i;

traffic_control DUT (n_lights,s_lights,e_lights,w_lights,clk,rst_a);

initial
 begin

$display("clk\t north\t south\t east\t west\t ");
$monitor("%b\t%b\t%b\t%b\t%b\t",clk,n_lights,s_lights,e_lights,w_lights);
$dumpfile("first.vcd");
$dumpvars(0,traffic_control_tb);


  clk=1'b1;
  for( i=0;i<100;i++)
    #5 clk=~clk;
 end

initial
 begin
  rst_a=1'b1;
  #15;
  rst_a=1'b0;
  #1000;
  $finish;
 end
endmodule

first.vcd
$date
	Fri May 03 10:11:55 2019
$end
$version
	Icarus Verilog
$end
$timescale
	1ps
$end
$scope module traffic_control_tb $end
$var wire 3 ! w_lights [2:0] $end
$var wire 3 " s_lights [2:0] $end
$var wire 3 # n_lights [2:0] $end
$var wire 3 $ e_lights [2:0] $end
$var reg 1 % clk $end
$var reg 1 & rst_a $end
$var integer 32 ' i [31:0] $end
$scope module DUT $end
$var wire 1 % clk $end
$var wire 3 ( east [2:0] $end
$var wire 3 ) east_y [2:0] $end
$var wire 3 * north [2:0] $end
$var wire 3 + north_y [2:0] $end
$var wire 1 & rst_a $end
$var wire 3 , south [2:0] $end
$var wire 3 - south_y [2:0] $end
$var wire 3 . west [2:0] $end
$var wire 3 / west_y [2:0] $end
$var reg 3 0 count [2:0] $end
$var reg 3 1 e_lights [2:0] $end
$var reg 3 2 n_lights [2:0] $end
$var reg 3 3 s_lights [2:0] $end
$var reg 3 4 state [2:0] $end
$var reg 3 5 w_lights [2:0] $end
$upscope $end
$upscope $end
$enddefinitions $end
#0
$dumpvars
b100 5
b0 4
b100 3
b1 2
b100 1
b0 0
b111 /
b110 .
b11 -
b10 ,
b1 +
b0 *
b101 )
b100 (
b0 '
1&
1%
b100 $
b1 #
b100 "
b100 !
$end
#5000
b1 '
0%
#10000
b10 '
1%
#15000
b11 '
0%
0&
#20000
b1 0
b100 '
1%
#25000
b101 '
0%
#30000
b10 0
b110 '
1%
#35000
b111 '
0%
#40000
b11 0
b1000 '
1%
#45000
b1001 '
0%
#50000
b100 0
b1010 '
1%
#55000
b1011 '
0%
#60000
b101 0
b1100 '
1%
#65000
b1101 '
0%
#70000
b110 0
b1110 '
1%
#75000
b1111 '
0%
#80000
b111 0
b10000 '
1%
#85000
b10001 '
0%
#90000
b10 #
b10 2
b1 4
b0 0
b10010 '
1%
#95000
b10011 '
0%
#100000
b1 0
b10100 '
1%
#105000
b10101 '
0%
#110000
b10 0
b10110 '
1%
#115000
b10111 '
0%
#120000
b11 0
b11000 '
1%
#125000
b11001 '
0%
#130000
b1 "
b1 3
b100 #
b100 2
b10 4
b0 0
b11010 '
1%
#135000
b11011 '
0%
#140000
b1 0
b11100 '
1%
#145000
b11101 '
0%
#150000
b10 0
b11110 '
1%
#155000
b11111 '
0%
#160000
b11 0
b100000 '
1%
#165000
b100001 '
0%
#170000
b100 0
b100010 '
1%
#175000
b100011 '
0%
#180000
b101 0
b100100 '
1%
#185000
b100101 '
0%
#190000
b110 0
b100110 '
1%
#195000
b100111 '
0%
#200000
b111 0
b101000 '
1%
#205000
b101001 '
0%
#210000
b10 "
b10 3
b11 4
b0 0
b101010 '
1%
#215000
b101011 '
0%
#220000
b1 0
b101100 '
1%
#225000
b101101 '
0%
#230000
b10 0
b101110 '
1%
#235000
b101111 '
0%
#240000
b11 0
b110000 '
1%
#245000
b110001 '
0%
#250000
b1 $
b1 1
b100 "
b100 3
b100 4
b0 0
b110010 '
1%
#255000
b110011 '
0%
#260000
b1 0
b110100 '
1%
#265000
b110101 '
0%
#270000
b10 0
b110110 '
1%
#275000
b110111 '
0%
#280000
b11 0
b111000 '
1%
#285000
b111001 '
0%
#290000
b100 0
b111010 '
1%
#295000
b111011 '
0%
#300000
b101 0
b111100 '
1%
#305000
b111101 '
0%
#310000
b110 0
b111110 '
1%
#315000
b111111 '
0%
#320000
b111 0
b1000000 '
1%
#325000
b1000001 '
0%
#330000
b10 $
b10 1
b101 4
b0 0
b1000010 '
1%
#335000
b1000011 '
0%
#340000
b1 0
b1000100 '
1%
#345000
b1000101 '
0%
#350000
b10 0
b1000110 '
1%
#355000
b1000111 '
0%
#360000
b11 0
b1001000 '
1%
#365000
b1001001 '
0%
#370000
b1 !
b1 5
b100 $
b100 1
b110 4
b0 0
b1001010 '
1%
#375000
b1001011 '
0%
#380000
b1 0
b1001100 '
1%
#385000
b1001101 '
0%
#390000
b10 0
b1001110 '
1%
#395000
b1001111 '
0%
#400000
b11 0
b1010000 '
1%
#405000
b1010001 '
0%
#410000
b100 0
b1010010 '
1%
#415000
b1010011 '
0%
#420000
b101 0
b1010100 '
1%
#425000
b1010101 '
0%
#430000
b110 0
b1010110 '
1%
#435000
b1010111 '
0%
#440000
b111 0
b1011000 '
1%
#445000
b1011001 '
0%
#450000
b10 !
b10 5
b0 0
b111 4
b1011010 '
1%
#455000
b1011011 '
0%
#460000
b1 0
b1011100 '
1%
#465000
b1011101 '
0%
#470000
b10 0
b1011110 '
1%
#475000
b1011111 '
0%
#480000
b11 0
b1100000 '
1%
#485000
b1100001 '
0%
#490000
b100 !
b100 5
b1 #
b1 2
b0 0
b0 4
b1100010 '
1%
#495000
b1100011 '
0%
#500000
b1 0
b1100100 '
1%
